mapchete_hub/__init__.py
mapchete_hub/_log.py
mapchete_hub/app.py
mapchete_hub/cluster.py
mapchete_hub/geometry.py
mapchete_hub/job_wrapper.py
mapchete_hub/k8s.py
mapchete_hub/lifespan_resources.py
mapchete_hub/models.py
mapchete_hub/random_names.py
mapchete_hub/settings.py
mapchete_hub/timetools.py
mapchete_hub/cli/__init__.py
mapchete_hub/cli/manager.py
mapchete_hub/cli/server.py
mapchete_hub/cli/worker.py
mapchete_hub/db/__init__.py
mapchete_hub/db/base.py
mapchete_hub/db/memory.py
mapchete_hub/db/mongodb.py
mapchete_hub/job_handler/__init__.py
mapchete_hub/job_handler/background_thread.py
mapchete_hub/job_handler/base.py
mapchete_hub/job_handler/k8s_worker.py
mapchete_hub/job_handler/mhub_worker.py
mapchete_hub/observers/__init__.py
mapchete_hub/observers/db_updater.py
mapchete_hub/observers/slack_messenger.py
mapchete_hub-2025.8.0.dist-info/METADATA
mapchete_hub-2025.8.0.dist-info/WHEEL
mapchete_hub-2025.8.0.dist-info/entry_points.txt
mapchete_hub-2025.8.0.dist-info/licenses/LICENSE
mapchete_hub-2025.8.0.dist-info/RECORD
