Metadata-Version: 2.4
Name: mapchete-hub
Version: 2025.8.0
Summary: distributed mapchete processing
Project-URL: Homepage, https://github.com/mapchete/mapchete-hub
Author-email: Joachim Ungar <joachim.ungar@eox.at>, Petr Sevcik <petr.sevcik@eox.at>
License-Expression: MIT
License-File: LICENSE
Classifier: Development Status :: 4 - Beta
Classifier: Intended Audience :: Developers
Classifier: License :: OSI Approved :: MIT License
Classifier: Programming Language :: Python :: 3.10
Classifier: Programming Language :: Python :: 3.11
Classifier: Programming Language :: Python :: 3.12
Classifier: Programming Language :: Python :: 3.13
Classifier: Topic :: Scientific/Engineering :: GIS
Requires-Dist: click<=8.1.3
Requires-Dist: dask
Requires-Dist: dask-gateway
Requires-Dist: distributed
Requires-Dist: fastapi
Requires-Dist: httpx
Requires-Dist: mapchete[contours,http,s3,vrt]>=2024.2.1
Requires-Dist: mongomock
Requires-Dist: pydantic-settings
Requires-Dist: pydantic>=2.0.0
Requires-Dist: pymongo
Requires-Dist: uvicorn
Requires-Dist: zarr
Provides-Extra: complete
Requires-Dist: bokeh; extra == 'complete'
Requires-Dist: click<=8.1.3; extra == 'complete'
Requires-Dist: dask; extra == 'complete'
Requires-Dist: dask-gateway; extra == 'complete'
Requires-Dist: distributed; extra == 'complete'
Requires-Dist: fastapi; extra == 'complete'
Requires-Dist: kubernetes; extra == 'complete'
Requires-Dist: mapchete[contours,http,s3,vrt]>=2024.2.1; extra == 'complete'
Requires-Dist: mongomock; extra == 'complete'
Requires-Dist: numcodecs; extra == 'complete'
Requires-Dist: pydantic-settings; extra == 'complete'
Requires-Dist: pydantic>=2.0.0; extra == 'complete'
Requires-Dist: pymongo; extra == 'complete'
Requires-Dist: slack-sdk; extra == 'complete'
Requires-Dist: uvicorn; extra == 'complete'
Requires-Dist: zarr; extra == 'complete'
Provides-Extra: kubernetes
Requires-Dist: kubernetes; extra == 'kubernetes'
Provides-Extra: slack
Requires-Dist: slack-sdk; extra == 'slack'
Provides-Extra: test
Requires-Dist: httpx; extra == 'test'
Requires-Dist: pytest; extra == 'test'
Requires-Dist: pytest-cov; extra == 'test'
Requires-Dist: pytest-env; extra == 'test'
Requires-Dist: pytest-mongodb; extra == 'test'
Requires-Dist: requests; extra == 'test'
Provides-Extra: xarray
Requires-Dist: xarray; extra == 'xarray'
Requires-Dist: zarr; extra == 'xarray'
